[
  {
    "url": "https://sacombank-sbj.com/blogs/bang-gia-bac/bang-ty-gia-bac-ngay-03-12-2025-bang-8",
    "title": "Bảng Tỷ Giá Bạc - Ngày 03/12/2025 - Bảng 8",
    "date": "2025-12-03",
    "silver_type": "bac miếng kim-phúc-lộc sbj 999 1 lượng",
    "buy": 2130000,
    "sell": 2184000,
    "effective_time": "15:20",
    "image_url": "https://cdn.hstatic.net/200000315699/file/l8_a170e8e3330a4e1e882f493f0699e4e0.png",
    "ocr_text": "sacombank-sbj\nbang gia bac\nbang: 08 ngay 03/12/2025\nhiéu luc ti: 15h20\nloai bag we ge\nmé s6:bm.qdtg.02a\nban hanh:( / /2025)\nbon vj tinh: vnb/luong\nbac miéng kim-phtic-léc sbj 999 1 ludng\n2.130.000\n2.184.000",
    "crawled_at": "2025-12-03T08:50:07.239282Z"
  },
  {
    "url": "https://sacombank-sbj.com/blogs/bang-gia-bac/bang-ty-gia-bac-ngay-03-12-2025-bang-7",
    "title": "Bảng Tỷ Giá Bạc - Ngày 03/12/2025 - Bảng 7",
    "date": "2025-12-03",
    "silver_type": "bac miếng kim-phúc-lộc sbj 999 1 lượng",
    "buy": 2127000,
    "sell": 2181000,
    "effective_time": "13:20",
    "image_url": "https://cdn.hstatic.net/200000315699/file/l7_acad247287814333b0603d37a2c624ec.png",
    "ocr_text": "sacombank-sbj\ncong ty vang bac ba quy\nbang gia bac\nbang: 07 ngay 03/12/2025\nhiéu luc ta: 13h20\nm 86: bm.qdtg.02a\nban hanh: ( / /2025)\ndon vj tinh: vnd/lugng\n(oat bac fcrmua [cia ban\nbac miéng kim-phic-léc sbj 999 1 ludng\n2.127.000\n2.181.000",
    "crawled_at": "2025-12-03T08:50:08.759872Z"
  },
  {
    "url": "https://sacombank-sbj.com/blogs/bang-gia-bac/bang-ty-gia-bac-ngay-03-12-2025-bang-6",
    "title": "Bảng Tỷ Giá Bạc - Ngày 03/12/2025 - Bảng 6",
    "date": "2025-12-03",
    "silver_type": "bac miếng kim-phúc-lộc sbj 999 1 lượng",
    "buy": 2124000,
    "sell": 2178000,
    "effective_time": null,
    "image_url": "https://cdn.hstatic.net/200000315699/file/l6_ba20c63471d84f37b9445c1fb71558d2.png",
    "ocr_text": "sacombank-sbj\nbang gia bac\nbang: 06 ngdy 03/12/2025\nhiéu lue ti: 1305\nmi s6: bm.qdtg.02a\nban hanh: ( / /2025)\nbon vi tinh: vnd/luong\nloalbac ff cumua | ciaean\nbac miéng kim-phic-léc sbj 999 1 lugng\n2.124.000\n2.178.000",
    "crawled_at": "2025-12-03T08:50:10.116801Z"
  },
  {
    "url": "https://sacombank-sbj.com/blogs/bang-gia-bac/bang-ty-gia-bac-ngay-03-12-2025-bang-5",
    "title": "Bảng Tỷ Giá Bạc - Ngày 03/12/2025 - Bảng 5",
    "date": "2025-12-03",
    "silver_type": "bac miếng kim-phúc-lộc sbj 999 1 lượng",
    "buy": 2151000,
    "sell": 2205000,
    "effective_time": "11:15",
    "image_url": "https://cdn.hstatic.net/200000315699/file/l5r_c7918b4e4f1c4a1ca5c0b9b096ce404b.png",
    "ocr_text": "sacombank-sbj\nbang gia bac\nbang: 05 ngay 03/12/2025\nhiéu luc ti: 11h15\nloai bag we ge\nmé s6:bm.qdtg.02a\nban hanh:( / /2025)\nbon vj tinh: vnb/luong\nbac miéng kim-phtic-léc sbj 999 1 ludng\n2.151.000\n2.205.000",
    "crawled_at": "2025-12-03T08:50:11.656051Z"
  },
  {
    "url": "https://sacombank-sbj.com/blogs/bang-gia-bac/bang-ty-gia-bac-ngay-03-12-2025-bang-4",
    "title": "Bảng Tỷ Giá Bạc - Ngày 03/12/2025 - Bảng 4",
    "date": "2025-12-03",
    "silver_type": "bac miếng kim-phúc-lộc sbj 999 1 lượng",
    "buy": 2148000,
    "sell": 2199000,
    "effective_time": "10:00",
    "image_url": "https://cdn.hstatic.net/200000315699/file/l4_16be74060d104b9699694b8211959bc5.png",
    "ocr_text": "sacombank-sbj\nsc...\nbang gia bac\nbang: 04 ngdy 03/12/2025\nhiéu lue ti: 10h00\nmi s6: bm.qdtg.02a\nban hanh: ( / /2025)\nbon vi tinh: vnd/luong\nloalbac ff cumua | ciaean\nbac miéng kim-phic-léc sbj 999 1 lugng\n2.148.000\n2.199.000",
    "crawled_at": "2025-12-03T08:50:13.010723Z"
  },
  {
    "url": "https://sacombank-sbj.com/blogs/bang-gia-bac/bang-ty-gia-bac-ngay-03-12-2025-bang-3",
    "title": "Bảng Tỷ Giá Bạc - Ngày 03/12/2025 - Bảng 3",
    "date": "2025-12-03",
    "silver_type": "bac miếng kim-phúc-lộc sbj 999 1 lượng",
    "buy": 2145000,
    "sell": 2196000,
    "effective_time": "08:56",
    "image_url": "https://cdn.hstatic.net/200000315699/file/l3_1c46573a0a6948108e9c55e09e2a6673_master.png",
    "ocr_text": "sacombank-sbj mg s6: bm.qdtg.02a\ncong ty vang bac da quy\nban hanh: ( / /2025)\nbang gia bac\nbang: 03 ngay 03/12/2025\nhiéu lwe tiv: 08h56 don vi tinh: vnd/luong\nloai bac gia mua gia ban\nbac miéng kim-phuc-léc sbj 999 1 lvong 2,145,000 2,196,000",
    "crawled_at": "2025-12-03T08:50:14.754191Z"
  },
  {
    "url": "https://sacombank-sbj.com/blogs/bang-gia-bac/bang-ty-gia-bac-ngay-03-12-2025-bang-2",
    "title": "Bảng Tỷ Giá Bạc - Ngày 03/12/2025 - Bảng 2",
    "date": "2025-12-03",
    "silver_type": "bac miếng kim-phúc-lộc sbj 999 1 lượng",
    "buy": 2139000,
    "sell": 2190000,
    "effective_time": "08:30",
    "image_url": "https://cdn.hstatic.net/200000315699/file/l2_a12904fe952a47e78590eb4c4f2e3843_master.png",
    "ocr_text": "sacombank-sbj ma s6: bm.qdtg.02a\ncong ty vang bac da quy\nban hanh: ( / /2025)\nbang gia bac\nbang: 02 ngay 03/12/2025\nhiéu lwe tiv: 08h30 don vi tinh: vnd/luong\nloai bac gia mua gia ban\nbac miéng kim-phuc-léc sbj 999 1 lvong 2,139,000 2,190,000",
    "crawled_at": "2025-12-03T08:50:16.753001Z"
  },
  {
    "url": "https://sacombank-sbj.com/blogs/bang-gia-bac/bang-ty-gia-bac-ngay-03-12-2025-bang-1",
    "title": "Bảng Tỷ Giá Bạc - Ngày 03/12/2025 - Bảng 1",
    "date": "2025-12-03",
    "silver_type": null,
    "buy": 2109000,
    "sell": 2160000,
    "effective_time": "07:30",
    "image_url": "https://cdn.hstatic.net/200000315699/file/hinh_anh_3-12-25_luc_07.22_750f578000fd44909257f4c985e4adad.jpeg",
    "ocr_text": "sacombank-sbj m6: bm.qdtg.02a\nne ban hanh:( / /2025)\nbang gia bac\nhiéu lure tir: 07h30 don vj tinh: vnd/uo‘ng\nloal bac [ciawua _gaban\nbac miéng kim-phtic-léc sbu 999 1 iuvo‘ng 2.109.000 2.160.000",
    "crawled_at": "2025-12-03T08:50:18.383071Z"
  },
  {
    "url": "https://sacombank-sbj.com/blogs/bang-gia-bac/bang-ty-gia-bac-ngay-02-12-2025-bang-9",
    "title": "Bảng Tỷ Giá Bạc - Ngày 02/12/2025 - Bảng 9",
    "date": "2025-12-02",
    "silver_type": "bac miếng kim-phúc-lộc sbj 999 1 lượng",
    "buy": 2100000,
    "sell": 2151000,
    "effective_time": "14:15",
    "image_url": "https://cdn.hstatic.net/200000315699/file/l9_34d6d9813ac0437e8c4b8e3465e22b66.png",
    "ocr_text": "sacombank-sbj mas: bm.qdtg.02a\ncong ty vang bac da quy\nban hanh: ( / /2025)\n‘s odaeseness\nbang gia bac\nhiéu lue tir: 14h15 don vi tinh: vnd/luong\nloa bag cima [cia pan\nbac miéng kim-phie-léc sbj 999 1 ludng 2.100.000 2.151.000",
    "crawled_at": "2025-12-03T08:50:19.930977Z"
  },
  {
    "url": "https://sacombank-sbj.com/blogs/bang-gia-bac/bang-ty-gia-bac-ngay-02-12-2025-bang-8",
    "title": "Bảng Tỷ Giá Bạc - Ngày 02/12/2025 - Bảng 8",
    "date": "2025-12-02",
    "silver_type": "bac miếng kim-phúc-lộc sbj 999 1 lượng",
    "buy": 2094000,
    "sell": 2145000,
    "effective_time": "13:45",
    "image_url": "https://cdn.hstatic.net/200000315699/file/l8_b9b20f24f6e34a6e9f4f92b549758da6.png",
    "ocr_text": "sacombank-sbj\ncong ty vang bac ba quy\nbang gia bac\nbang: 08 ngay 02/12/2025\nhiéu luc ta: 13h45\nm 86: bm.qdtg.02a\nban hanh: ( / /2025)\ndon vj tinh: vnd/lugng\n(oat bac fcrmua [cia ban\nbac miéng kim-phic-léc sbj 999 1 ludng\n2.094.000\n2.145.000",
    "crawled_at": "2025-12-03T08:50:21.386920Z"
  },
  {
    "url": "https://sacombank-sbj.com/blogs/bang-gia-bac/bang-ty-gia-bac-ngay-02-12-2025-bang-7",
    "title": "Bảng Tỷ Giá Bạc - Ngày 02/12/2025 - Bảng 7",
    "date": "2025-12-02",
    "silver_type": "bac miếng kim-phúc-lộc sbj 999 1 lượng",
    "buy": 2106000,
    "sell": 2157000,
    "effective_time": null,
    "image_url": "https://cdn.hstatic.net/200000315699/file/l7_fcecc1709a604ba7903ccfd7a39cd13c.png",
    "ocr_text": "sacombank-sbj\nbang gia bac\nbang: 07 ngdy 02/12/2025\nhiéu lye ti: 1370\nmi s6: bm.qdtg.02a\nban hanh: ( / /2025)\nbon vi tinh: vnd/luong\nloalbac ff cumua | ciaean\nbac miéng kim-phic-léc sbj 999 1 lugng\n2.106.000\n2.157.000",
    "crawled_at": "2025-12-03T08:50:22.960792Z"
  },
  {
    "url": "https://sacombank-sbj.com/blogs/bang-gia-bac/bang-ty-gia-bac-ngay-02-12-2025-bang-6",
    "title": "Bảng Tỷ Giá Bạc - Ngày 02/12/2025 - Bảng 6",
    "date": "2025-12-02",
    "silver_type": "bac miếng kim-phúc-lộc sbj 999 1 lượng",
    "buy": 2100000,
    "sell": 2151000,
    "effective_time": "11:10",
    "image_url": "https://cdn.hstatic.net/200000315699/file/l6_5fdac480af5d400d82de6508c2c6431e.png",
    "ocr_text": "sacombank-sbj m4 86: bm.qdtg.02a\nban hanh: ( / /2025)\nsikrcen\nbang gia bac\nhiéu luc ta: 11h10 bon vj tinh: vnd/lugng\nloalbac ff cumua | ciaean\nbac miéng kim-phiic-léc sbj 999 1 lung 2.100.000 2.151.000",
    "crawled_at": "2025-12-03T08:50:24.551173Z"
  },
  {
    "url": "https://sacombank-sbj.com/blogs/bang-gia-bac/bang-ty-gia-bac-ngay-02-12-2025-bang-5",
    "title": "Bảng Tỷ Giá Bạc - Ngày 02/12/2025 - Bảng 5",
    "date": "2025-12-02",
    "silver_type": "bac miếng kim-phúc-lộc sbj 999 1 lượng",
    "buy": 2106000,
    "sell": 2157000,
    "effective_time": "10:22",
    "image_url": "https://cdn.hstatic.net/200000315699/file/l5_7c05e3ca13344ee7b36416ef227c291a.png",
    "ocr_text": "sacombank-sbj\ncong ty vang bac ba quy\nbang gia bac\nbang: 05 ngay 02/12/2025\nhiéu luc ta: 10h22\nm 86: bm.qdtg.02a\nban hanh: ( / /2025)\ndon vj tinh: vnd/lugng\n(oat bac fcrmua [cia ban\nbac miéng kim-phic-léc sbj 999 1 ludng\n2.106.000\n2.157.000",
    "crawled_at": "2025-12-03T08:50:25.901565Z"
  },
  {
    "url": "https://sacombank-sbj.com/blogs/bang-gia-bac/bang-ty-gia-bac-ngay-02-12-2025-bang-4",
    "title": "Bảng Tỷ Giá Bạc - Ngày 02/12/2025 - Bảng 4",
    "date": "2025-12-02",
    "silver_type": "bac miếng kim-phúc-lộc sbj 999 1 lượng",
    "buy": 2100000,
    "sell": 2151000,
    "effective_time": null,
    "image_url": "https://cdn.hstatic.net/200000315699/file/l4_11b49710c66f4f88955c137ca23f2873.png",
    "ocr_text": "sacombank-sbj m4 86: bm.qdtg.02a\nban hanh: ( / /2025)\ns6::\nbang gia bac\nhiéu luc ta: o9hs2 bon vj tinh: vnd/lugng\nloalbac ff cumua | ciaean\nbac miéng kim-phiic-léc sbj 999 1 lung 2.100.000 2.151.000",
    "crawled_at": "2025-12-03T08:50:27.357235Z"
  },
  {
    "url": "https://sacombank-sbj.com/blogs/bang-gia-bac/bang-ty-gia-bac-ngay-02-12-2025-bang-3",
    "title": "Bảng Tỷ Giá Bạc - Ngày 02/12/2025 - Bảng 3",
    "date": "2025-12-02",
    "silver_type": "bac miếng kim-phúc-lộc sbj 999 1 lượng",
    "buy": 2091000,
    "sell": 2142000,
    "effective_time": "09:25",
    "image_url": "https://cdn.hstatic.net/200000315699/file/l3_be28a53ec7114607976f4e78f666dc6c_master.png",
    "ocr_text": "sacomb ank-sbj m& s6: bm.qdtg.02a\nban hanh: ( / /2025)\nbang gia bac\nhiéu lic tiv: 09h25 don vi tinh: vnd/luong\nloai bac gia mua gia ban\nbac miéng kim-phiic-léc sbj 999 1 long 2,091,000 2,142,000",
    "crawled_at": "2025-12-03T08:50:28.851315Z"
  },
  {
    "url": "https://sacombank-sbj.com/blogs/bang-gia-bac/bang-ty-gia-bac-ngay-02-12-2025-bang-2",
    "title": "Bảng Tỷ Giá Bạc - Ngày 02/12/2025 - Bảng 2",
    "date": "2025-12-02",
    "silver_type": "bac miếng kim-phúc-lộc sbj 999 1 lượng",
    "buy": 2085000,
    "sell": 2136000,
    "effective_time": "09:00",
    "image_url": "https://cdn.hstatic.net/200000315699/file/l2_a42db074c1ac4e50995d89d87eb1495e.png",
    "ocr_text": "sacombank-sbj\ncong ty vang bac ba quy\nbang gia bac\nbang: 02 ngay 02/12/2025\nhiéu luc ta: 09h00\nm 86: bm.qdtg.02a\nban hanh: ( / /2025)\ndon vj tinh: vnd/lugng\n(oat bac fcrmua [cia ban\nbac miéng kim-phuc-léc sbj 999 1 luong\n2.085.000\n2.136.000",
    "crawled_at": "2025-12-03T08:50:30.410433Z"
  },
  {
    "url": "https://sacombank-sbj.com/blogs/bang-gia-bac/bang-ty-gia-bac-ngay-02-12-2025-bang-12",
    "title": "Bảng Tỷ Giá Bạc - Ngày 02/12/2025 - Bảng 12",
    "date": "2025-12-02",
    "silver_type": "bac miếng kim-phúc-lộc sbj 999 1 lượng",
    "buy": 2094000,
    "sell": 2145000,
    "effective_time": "16:52",
    "image_url": "https://cdn.hstatic.net/200000315699/file/l12_0db5073bc56a4459bf39007151b88e2d.png",
    "ocr_text": "sacombank-sbj mé 86: bm.qdtg.02a\nban hanh:( / /2025)\nbang gia bac\nhiéu luc ta: 16h52 bon vj tinh: vnb/luong\n(oat bac fcrmua [cia ban\nbac miéng kim-phic-léc sbj 999 1 ludng 2.094.000 2.145.000",
    "crawled_at": "2025-12-03T08:50:32.027254Z"
  },
  {
    "url": "https://sacombank-sbj.com/blogs/bang-gia-bac/bang-ty-gia-bac-ngay-02-12-2025-bang-11",
    "title": "Bảng Tỷ Giá Bạc - Ngày 02/12/2025 - Bảng 11",
    "date": "2025-12-02",
    "silver_type": "bac miếng kim-phúc-lộc sbj 999 1 lượng",
    "buy": 2100000,
    "sell": 2151000,
    "effective_time": "16:25",
    "image_url": "https://cdn.hstatic.net/200000315699/file/l11_8cee48772a5940df85f2510b108cefe0.png",
    "ocr_text": "sacombank-sbj\ncong ty vang bac ba quy\nbang gia bac\nbang: 11 ngay 02/12/2025\nhiéu luc ta: 16h25\nm 86: bm.qdtg.02a\nban hanh: ( / /2025)\ndon vj tinh: vnd/lugng\nbac fcrmua [cia ban\nbac miéng kim-phic-léc sbj 999 1 ludng\n2.100.000\n2.151.000",
    "crawled_at": "2025-12-03T08:50:33.386319Z"
  },
  {
    "url": "https://sacombank-sbj.com/blogs/bang-gia-bac/bang-ty-gia-bac-ngay-02-12-2025-bang-10",
    "title": "Bảng Tỷ Giá Bạc - Ngày 02/12/2025 - Bảng 10",
    "date": "2025-12-02",
    "silver_type": "bac miếng kim-phúc-l6éc sbj 999 1 lworng",
    "buy": 2106000,
    "sell": 2157000,
    "effective_time": "14:43",
    "image_url": "https://cdn.hstatic.net/200000315699/file/l10_fadc70cb2fec447cbd95b31e3a7780af_master.png",
    "ocr_text": "sacombank-sbj ma sé: bm.qdtg.02a\n' ban hanh: ( / /2025)\ns6:\npnomaccona bang gia bac\nbang: 10 ngay 02/12/2025\nhiéu luc tw: 14h43 don vi tinh: vnd/luong\nloaibac pcamus | cikban\nbac miéng kim-phic-l6éc sbj 999 1 lworng 2,106,000\n2,157,000",
    "crawled_at": "2025-12-03T08:50:37.119781Z"
  },
  {
    "url": "https://sacombank-sbj.com/blogs/bang-gia-bac/bang-ty-gia-bac-ngay-02-12-2025-bang-1",
    "title": "Bảng Tỷ Giá Bạc - Ngày 02/12/2025 - Bảng 1",
    "date": "2025-12-02",
    "silver_type": "bac miếng kim-phúc-lộc sbj 999 1 lu’o‘ng",
    "buy": 2115000,
    "sell": 2166000,
    "effective_time": "07:30",
    "image_url": "https://cdn.hstatic.net/200000315699/file/hinh_anh_2-12-25_luc_07.21_def4e8201a65406ba305479698ccaf57.jpeg",
    "ocr_text": "sacombank-sbj ma s6: bm.qdtg.02a\nne ban hanh:( / /2025)\nbang gia bac\nhiéu lure tir: 07h30 don vj tinh: vnd/uo‘ng\nloa bac [ciawua _giaban\nbac miéng kim-phtic-léc sbj 999 1 lu’o‘ng 2.115.000 2.166.000",
    "crawled_at": "2025-12-03T08:50:38.684905Z"
  },
  {
    "url": "https://sacombank-sbj.com/blogs/bang-gia-bac/bang-ty-gia-bac-ngay-01-12-2025-bang-9",
    "title": "Bảng Tỷ Giá Bạc - Ngày 01/12/2025 - Bảng 9",
    "date": "2025-12-01",
    "silver_type": "bac miếng kim-phúc-lộc sbj 999 1 lượng",
    "buy": 2103000,
    "sell": 2154000,
    "effective_time": null,
    "image_url": "https://cdn.hstatic.net/200000315699/file/l9_5c429386e5db40caa51b444db0a0f37a.png",
    "ocr_text": "sacombank-sbj ma sé: bm.qdtg.02a\neer brecoatguy eola ete\ns6:..\nbang gia bac\nhiéu luc ti: 16438 bon vj tinh: vnb/luong\nloalbac ff ckmua | onan\nbac miéng kim-phuc-léc sbj 999 1 lugng 2.103.000 2.154.000",
    "crawled_at": "2025-12-03T08:50:39.981764Z"
  },
  {
    "url": "https://sacombank-sbj.com/blogs/bang-gia-bac/bang-ty-gia-bac-ngay-01-12-2025-bang-8",
    "title": "Bảng Tỷ Giá Bạc - Ngày 01/12/2025 - Bảng 8",
    "date": "2025-12-01",
    "silver_type": "bac miếng kim-phúc-lộc sbj 999 1 lượng",
    "buy": 2091000,
    "sell": 2142000,
    "effective_time": "15:20",
    "image_url": "https://cdn.hstatic.net/200000315699/file/l8_037411e793fc46b0bd7d0b1d183e8cdf.png",
    "ocr_text": "sacombank-sbj\nbang gia bac\nbang: 08 ngdy 01/12/2025\nhiéu lye ti: 15h20\nmi s6: bm.qdtg.02a\nban hanh: ( / /2025)\nbon vi tinh: vnd/luong\nloalbac ff cumua | ciaean\nbac miéng kim-phic-léc sbj 999 1 lugng\n2.091.000\n2.142.000",
    "crawled_at": "2025-12-03T08:50:41.535004Z"
  },
  {
    "url": "https://sacombank-sbj.com/blogs/bang-gia-bac/bang-ty-gia-bac-ngay-01-12-2025-bang-7",
    "title": "Bảng Tỷ Giá Bạc - Ngày 01/12/2025 - Bảng 7",
    "date": "2025-12-01",
    "silver_type": null,
    "buy": 2088000,
    "sell": 2139000,
    "effective_time": "14:15",
    "image_url": "https://cdn.hstatic.net/200000315699/file/hinh_anh_1-12-25_luc_14.11_a3171d6a766449bfbb638263dba9e397.jpeg",
    "ocr_text": "sacombank-sbj mg s6: bm.qdtg.02a\nong ty vang bac ga auy conned, poe\nbang gia bac\nhiéu lure tir: 14h15 don vj tinh: vnd/uro‘ng\nloa bac [ciauua_giaban\nbac miéng kim-phtic-léc sbu 999 1 iuro‘ng 2.088.000 2.139.000",
    "crawled_at": "2025-12-03T08:50:43.376843Z"
  },
  {
    "url": "https://sacombank-sbj.com/blogs/bang-gia-bac/bang-ty-gia-bac-ngay-01-12-2025-bang-6",
    "title": "Bảng Tỷ Giá Bạc - Ngày 01/12/2025 - Bảng 6",
    "date": "2025-12-01",
    "silver_type": "bac miếng kim-phúc-lộc sbj 999 1 lượng",
    "buy": 2091000,
    "sell": 2142000,
    "effective_time": "13:10",
    "image_url": "https://cdn.hstatic.net/200000315699/file/l6_67822a1823464861b32c933600d38dd9.png",
    "ocr_text": "sacombank-sbj m& 86: bm.qdtg.02a\ncong ty vang bac ba quy\nban hanh: ( / /2025)\ns6:.\nbang gia bac\nhiéu lue tir: 13h10 don vi tinh: vnd/luong\nloa bag cima [cia pan\nbac miéng kim-phie-léc sbj 999 1 ludng 2.091.000 2.142.000",
    "crawled_at": "2025-12-03T08:50:44.807225Z"
  },
  {
    "url": "https://sacombank-sbj.com/blogs/bang-gia-bac/bang-ty-gia-bac-ngay-01-12-2025-bang-5",
    "title": "Bảng Tỷ Giá Bạc - Ngày 01/12/2025 - Bảng 5",
    "date": "2025-12-01",
    "silver_type": "bac miếng kim-phúc-lộc sbj 999 1 lượng",
    "buy": 2100000,
    "sell": 2151000,
    "effective_time": "11:17",
    "image_url": "https://cdn.hstatic.net/200000315699/file/l5_86246300dc8e432a9b7e7946d383df2f.png",
    "ocr_text": "sacombank-sbj m4 86: bm.qdtg.02a\nban hanh: ( / /2025)\nbang gia bac\nbang: 05 ngdy 01/12/2025\nhiéu luc ta: 11h17 bon vj tinh: vnd/lugng\nloalbac ff cumua | ciaean\nbac miéng kim-phiic-léc sbj 999 1 lung 2.100.000 2.151.000",
    "crawled_at": "2025-12-03T08:50:46.289544Z"
  },
  {
    "url": "https://sacombank-sbj.com/blogs/bang-gia-bac/bang-ty-gia-bac-ngay-01-12-2025-bang-4",
    "title": "Bảng Tỷ Giá Bạc - Ngày 01/12/2025 - Bảng 4",
    "date": "2025-12-01",
    "silver_type": "bac miếng kim-phúc-lộc sbj 999 1 lượng",
    "buy": 2109000,
    "sell": 2160000,
    "effective_time": "10:50",
    "image_url": "https://cdn.hstatic.net/200000315699/file/l4_b941ca6ad89348efbe13f781dce5e95c.png",
    "ocr_text": "sacombank-sbj\nbang gia bac\nbang: 04 ngdy 01/12/2025\nhiéu lue ti: 10h50\nmi s6: bm.qdtg.02a\nban hanh: ( / /2025)\nbon vi tinh: vnd/luong\nloalbac ff cumua | ciaean\nbac miéng kim-phic-léc sbj 999 1 lugng\n2.109.000\n2.160.000",
    "crawled_at": "2025-12-03T08:50:48.107018Z"
  },
  {
    "url": "https://sacombank-sbj.com/blogs/bang-gia-bac/bang-ty-gia-bac-ngay-01-12-2025-bang-3",
    "title": "Bảng Tỷ Giá Bạc - Ngày 01/12/2025 - Bảng 3",
    "date": "2025-12-01",
    "silver_type": "bac miếng kim-phúc-lộc sbj 999 1 lượng",
    "buy": 2094000,
    "sell": 2145000,
    "effective_time": "10:10",
    "image_url": "https://cdn.hstatic.net/200000315699/file/l3_4e83773d24f944c2b34c75d5b123ead1.png",
    "ocr_text": "sacombank-sbj\ncong ty vang bac ba quy\nbang gia bac\nbang: 03 ngday 01/12/2025\nhiéu luc ta: 10h10\nm 86: bm.qdtg.02a\nban hanh: ( / /2025)\ndon vj tinh: vnd/lugng\n(oat bac fcrmua [cia ban\nbac miéng kim-phic-léc sbj 999 1 ludng\n2.094.000\n2.145.000",
    "crawled_at": "2025-12-03T08:50:49.828245Z"
  }
]