{"phantich_cactuan": [{"volume_trungbinh": 9329.21875, "phantu_dautuan": {"id": 8450, "timestamp": "2025-12-19 08:05:00", "symbol": "XAUUSD", "open_price": 4323.03, "high_price": 4327.42, "low_price": 4322.47, "close_price": 4325.47, "volume": 9222.0, "created_at": "2025-12-19 08:08:34", "minute": "5"}, "phantu_cuoituan": {"id": 3105296, "timestamp": "2025-12-29 15:50:00", "symbol": "XAUUSD", "open_price": 4461.18, "high_price": 4464.73, "low_price": 4456.675, "close_price": 4458.658, "volume": 7834.0, "created_at": "2025-12-29 15:52:28", "minute": "5"}, "ti_le_tang_truong": 3.1956752555499395}, {"volume_trungbinh": 9779.06388888889, "phantu_dautuan": {"id": 6840, "timestamp": "2025-12-12 02:05:00", "symbol": "XAUUSD", "open_price": 4271.02, "high_price": 4271.44, "low_price": 4262.885, "close_price": 4266.026, "volume": 13764.0, "created_at": "2025-12-12 10:08:21", "minute": "5"}, "phantu_cuoituan": {"id": 8449, "timestamp": "2025-12-19 08:00:00", "symbol": "XAUUSD", "open_price": 4325.81, "high_price": 4327.295, "low_price": 4319.91, "close_price": 4323.079, "volume": 18259.0, "created_at": "2025-12-19 08:08:34", "minute": "5"}, "ti_le_tang_truong": 1.2828317357446222}, {"volume_trungbinh": 9145.736111111111, "phantu_dautuan": {"id": 881, "timestamp": "2025-12-04 21:05:00", "symbol": "XAUUSD", "open_price": 4199.02, "high_price": 4206.25, "low_price": 4198.345, "close_price": 4205.6, "volume": 14626.0, "created_at": "2025-12-04 21:25:56", "minute": "5"}, "phantu_cuoituan": {"id": 6839, "timestamp": "2025-12-12 02:00:00", "symbol": "XAUUSD", "open_price": 4268.12, "high_price": 4270.92, "low_price": 4262.305, "close_price": 4270.786, "volume": 16660.0, "created_at": "2025-12-12 10:08:21", "minute": "5"}, "ti_le_tang_truong": 1.6456220737219505}, {"volume_trungbinh": 8627.559722222222, "phantu_dautuan": {"id": 3192, "timestamp": "2025-11-27 11:20:00", "symbol": "XAUUSD", "open_price": 4147.33, "high_price": 4148.247, "low_price": 4146.07, "close_price": 4147.891, "volume": 5923.0, "created_at": "2025-12-09 12:40:08", "minute": "5"}, "phantu_cuoituan": {"id": 880, "timestamp": "2025-12-04 21:00:00", "symbol": "XAUUSD", "open_price": 4198.31, "high_price": 4200.98, "low_price": 4198.045, "close_price": 4198.91, "volume": 13145.0, "created_at": "2025-12-04 21:25:56", "minute": "5"}, "ti_le_tang_truong": 1.2292245854561965}, {"volume_trungbinh": 9660.290277777778, "phantu_dautuan": {"id": 3771, "timestamp": "2025-11-20 06:20:00", "symbol": "XAUUSD", "open_price": 4090.2, "high_price": 4090.967, "low_price": 4086.98, "close_price": 4088.387, "volume": 4226.0, "created_at": "2025-12-09 12:40:08", "minute": "5"}, "phantu_cuoituan": {"id": 3191, "timestamp": "2025-11-27 11:15:00", "symbol": "XAUUSD", "open_price": 4147.276, "high_price": 4148.27, "low_price": 4146.58, "close_price": 4147.191, "volume": 5479.0, "created_at": "2025-12-09 12:40:08", "minute": "5"}, "ti_le_tang_truong": 1.3954329861620465}, {"volume_trungbinh": 10748.725, "phantu_dautuan": {"id": 4654, "timestamp": "2025-11-13 00:20:00", "symbol": "XAUUSD", "open_price": 4192.93, "high_price": 4197.956, "low_price": 4192.625, "close_price": 4197.92, "volume": 14565.0, "created_at": "2025-12-09 12:40:08", "minute": "5"}, "phantu_cuoituan": {"id": 3770, "timestamp": "2025-11-20 06:15:00", "symbol": "XAUUSD", "open_price": 4088.26, "high_price": 4091.21, "low_price": 4087.115, "close_price": 4090.147, "volume": 5317.0, "created_at": "2025-12-09 12:40:08", "minute": "5"}, "ti_le_tang_truong": -2.4963450379567527}, {"volume_trungbinh": 4553.902083333333, "phantu_dautuan": {"id": 5589, "timestamp": "2025-11-10 06:00:00", "symbol": "XAUUSD", "open_price": 3998.91, "high_price": 4010.69, "low_price": 3997.198, "close_price": 4006.56, "volume": 7302.0, "created_at": "2025-12-09 12:40:08", "minute": "5"}, "phantu_cuoituan": {"id": 4653, "timestamp": "2025-11-13 00:15:00", "symbol": "XAUUSD", "open_price": 4198.8, "high_price": 4199.663, "low_price": 4192.16, "close_price": 4193.19, "volume": 15993.0, "created_at": "2025-12-09 12:40:08", "minute": "5"}, "ti_le_tang_truong": 4.9986121218032}], "tongket_phantich_toanbo": {"volume_trungbinh": 9461.97131321717, "phantu_dautuan": {"id": 3105296, "timestamp": "2025-12-29 15:50:00", "symbol": "XAUUSD", "open_price": 4461.18, "high_price": 4464.73, "low_price": 4456.675, "close_price": 4458.658, "volume": 7834.0, "created_at": "2025-12-29 15:52:28", "minute": "5"}, "phantu_cuoituan": {"id": 5589, "timestamp": "2025-11-10 06:00:00", "symbol": "XAUUSD", "open_price": 3998.91, "high_price": 4010.69, "low_price": 3997.198, "close_price": 4006.56, "volume": 7302.0, "created_at": "2025-12-09 12:40:08", "minute": "5"}, "ti_le_tang_truong": 11.55990007276984}}