{"phantich_cactuan": [{"volume_trungbinh": 9072.164583333333, "phantu_dautuan": {"id": 1285, "timestamp": "2025-12-06 04:50:00", "symbol": "XAUUSD", "open_price": 4196.59, "high_price": 4198.39, "low_price": 4194.65, "close_price": 4196.311, "volume": 6554.0, "created_at": "2025-12-06 09:15:50", "minute": "5"}, "phantu_cuoituan": {"id": 7095, "timestamp": "2025-12-12 21:25:00", "symbol": "XAUUSD", "open_price": 4339.44, "high_price": 4344.69, "low_price": 4338.79, "close_price": 4344.455, "volume": 5628.0, "created_at": "2025-12-12 21:27:14", "minute": "5"}, "ti_le_tang_truong": 3.403954162784533}, {"volume_trungbinh": 9787.99513888889, "phantu_dautuan": {"id": 2150, "timestamp": "2025-12-01 17:00:00", "symbol": "XAUUSD", "open_price": 4249.755, "high_price": 4259.57, "low_price": 4248.888, "close_price": 4258.78, "volume": 10635.0, "created_at": "2025-12-09 12:40:08", "minute": "5"}, "phantu_cuoituan": {"id": 1560, "timestamp": "2025-12-06 04:50:00", "symbol": "XAUUSD", "open_price": 4196.59, "high_price": 4198.39, "low_price": 4194.65, "close_price": 4196.115, "volume": 6557.0, "created_at": "2025-12-08 20:34:55", "minute": "5"}, "ti_le_tang_truong": -1.2510132937075187}, {"volume_trungbinh": 7981.065277777778, "phantu_dautuan": {"id": 3426, "timestamp": "2025-11-24 07:15:00", "symbol": "XAUUSD", "open_price": 4061.921, "high_price": 4064.08, "low_price": 4058.82, "close_price": 4062.13, "volume": 5754.0, "created_at": "2025-12-09 12:40:08", "minute": "5"}, "phantu_cuoituan": {"id": 2149, "timestamp": "2025-12-01 16:55:00", "symbol": "XAUUSD", "open_price": 4245.066, "high_price": 4250.826, "low_price": 4243.415, "close_price": 4249.91, "volume": 9354.0, "created_at": "2025-12-09 12:40:08", "minute": "5"}, "ti_le_tang_truong": 4.508827227314367}, {"volume_trungbinh": 10765.804861111112, "phantu_dautuan": {"id": 5217, "timestamp": "2025-11-15 01:15:00", "symbol": "XAUUSD", "open_price": 4094.641, "high_price": 4095.277, "low_price": 4086.205, "close_price": 4089.03, "volume": 13981.0, "created_at": "2025-12-09 12:40:08", "minute": "5"}, "phantu_cuoituan": {"id": 3425, "timestamp": "2025-11-24 07:10:00", "symbol": "XAUUSD", "open_price": 4060.65, "high_price": 4063.36, "low_price": 4057.935, "close_price": 4062.06, "volume": 8308.0, "created_at": "2025-12-09 12:40:08", "minute": "5"}, "ti_le_tang_truong": -0.8301338261400691}, {"volume_trungbinh": 8968.345833333333, "phantu_dautuan": {"id": 5589, "timestamp": "2025-11-10 06:00:00", "symbol": "XAUUSD", "open_price": 3998.91, "high_price": 4010.69, "low_price": 3997.198, "close_price": 4006.56, "volume": 7302.0, "created_at": "2025-12-09 12:40:08", "minute": "5"}, "phantu_cuoituan": {"id": 5216, "timestamp": "2025-11-15 01:10:00", "symbol": "XAUUSD", "open_price": 4091.421, "high_price": 4095.767, "low_price": 4088.31, "close_price": 4094.69, "volume": 13327.0, "created_at": "2025-12-09 12:40:08", "minute": "5"}, "ti_le_tang_truong": 2.3134054029723092}], "tongket_phantich_toanbo": {"volume_trungbinh": 9452.930373502466, "phantu_dautuan": {"id": 7095, "timestamp": "2025-12-12 21:25:00", "symbol": "XAUUSD", "open_price": 4339.44, "high_price": 4344.69, "low_price": 4338.79, "close_price": 4344.455, "volume": 5628.0, "created_at": "2025-12-12 21:27:14", "minute": "5"}, "phantu_cuoituan": {"id": 5589, "timestamp": "2025-11-10 06:00:00", "symbol": "XAUUSD", "open_price": 3998.91, "high_price": 4010.69, "low_price": 3997.198, "close_price": 4006.56, "volume": 7302.0, "created_at": "2025-12-09 12:40:08", "minute": "5"}, "ti_le_tang_truong": 8.515570492959325}}